feelfree/__init__.py
feelfree-0.11.dist-info/LICENSE
feelfree-0.11.dist-info/METADATA
feelfree-0.11.dist-info/WHEEL
feelfree-0.11.dist-info/top_level.txt
feelfree-0.11.dist-info/RECORD
