Metadata-Version: 2.1
Name: feelfree
Version: 0.11
Summary: The free version of FEEL package
Home-page: https://github.com/fangj99/feelfree
Author: Lau & Fang
Author-email: fangj99@gmail.com
License: GNU
Platform: UNKNOWN
Classifier: Programming Language :: Python :: 3
Classifier: Operating System :: OS Independent
